{
    "BlueArchiveRole": {
        "月雪 都子(ミヤコ/Miyako)": {
            "屬性": "貫通",
            "裝甲": "重裝",
            "武器": "SMG衝鋒槍",
            "定位": "前衛(控場)",
            "新手期": 3,
            "總力戰": 2,
            "大決戰": 2,
            "演習考試": 2,
            "戰術對抗": 3,
            "高難活動": 3,
            "泛用評級": 50,
            "IMG_URL": "https://i.imgur.com/UZAKQcj.png"
        },
        "空井 咲希(サキ/Saki)": {
            "屬性": "貫通",
            "裝甲": "特殊",
            "武器": "MG機槍",
            "定位": "前衛(控場AOE)",
            "新手期": 3,
            "總力戰": 2,
            "大決戰": 3,
            "演習考試": 3,
            "戰術對抗": 0,
            "高難活動": 3,
            "泛用評級": 60,
            "IMG_URL": "https://i.imgur.com/JUCoolS.png"
        },
        "風倉 萌(モエ/Moe)": {
            "屬性": "貫通",
            "裝甲": "特殊",
            "武器": "HG手槍",
            "定位": "後衛(輸出AOE)",
            "新手期": 3,
            "總力戰": 3,
            "大決戰": 3,
            "演習考試": 3,
            "戰術對抗": 3,
            "高難活動": 3,
            "泛用評級": 60,
            "IMG_URL": "https://i.imgur.com/ttysc5l.png"
        },
        "霞沢 美優(ミユ/Miyu)": {
            "屬性": "貫通",
            "裝甲": "輕裝",
            "武器": "SR狙擊槍",
            "定位": "前衛(輸出)",
            "新手期": 3,
            "總力戰": 4,
            "大決戰": 4,
            "演習考試": 3,
            "戰術對抗": 0,
            "高難活動": 2,
            "泛用評級": 70,
            "IMG_URL": "https://i.imgur.com/YG63lda.png"
        },
        "音瀨 小玉(コタマ/Kotama)": {
            "屬性": "爆發",
            "裝甲": "輕裝",
            "武器": "HG手槍",
            "定位": "後衛(輔助)",
            "新手期": 4,
            "總力戰": 4,
            "大決戰": 4,
            "演習考試": 4,
            "戰術對抗": 0,
            "高難活動": 3,
            "泛用評級": 80,
            "IMG_URL": "https://i.imgur.com/ge0bnAy.png"
        },
        "小鉤 晴(ハレ/Hare)": {
            "屬性": "爆發",
            "裝甲": "輕裝",
            "武器": "AR突擊槍",
            "定位": "後衛(輔助)",
            "新手期": 0,
            "總力戰": 2,
            "大決戰": 2,
            "演習考試": 0,
            "戰術對抗": 0,
            "高難活動": 2,
            "泛用評級": 40,
            "IMG_URL": "https://i.imgur.com/E4toqKC.png"
        },
        "和泉元 英美(エイミ/Eimi)": {
            "屬性": "爆發",
            "裝甲": "輕裝",
            "武器": "SG霞彈槍",
            "定位": "前衛(生存)",
            "新手期": 0,
            "總力戰": 4,
            "大決戰": 4,
            "演習考試": 3,
            "戰術對抗": 2,
            "高難活動": 3,
            "泛用評級": 70,
            "IMG_URL": "https://i.imgur.com/6MmGfzC.png"
        },
        "豊見 亞都梨(コトリ/Kotori)": {
            "屬性": "貫通",
            "裝甲": "輕裝",
            "武器": "MG機槍",
            "定位": "前衛(輔助, 位移)",
            "新手期": 0,
            "總力戰": 2,
            "大決戰": 2,
            "演習考試": 0,
            "戰術對抗": 0,
            "高難活動": 0,
            "泛用評級": 50,
            "IMG_URL": "https://i.imgur.com/izIqd3L.png"
        },
        "飛鳥馬 季(トキ/Toki)": {
            "屬性": "爆發",
            "裝甲": "彈力",
            "武器": "AR突擊槍",
            "定位": "前衛(輸出)",
            "新手期": 3,
            "總力戰": 3,
            "大決戰": 4,
            "演習考試": 3,
            "戰術對抗": 0,
            "高難活動": 3,
            "泛用評級": 63,
            "IMG_URL": "https://i.imgur.com/F92klLd.png"
        },
        "天童 愛麗絲(アリス/Arisu)": {
            "屬性": "神秘",
            "裝甲": "特殊",
            "武器": "RG磁軌砲",
            "定位": "前衛(輸出AOE)",
            "新手期": 4,
            "總力戰": 3,
            "大決戰": 3,
            "演習考試": 4,
            "戰術對抗": 3,
            "高難活動": 3,
            "泛用評級": 66,
            "IMG_URL": "https://i.imgur.com/pFZ7BLn.png"
        },
        "室笠 朱音(アカネ/Akane)": {
            "屬性": "貫通",
            "裝甲": "輕裝",
            "武器": "HG手槍",
            "定位": "前衛(破防)",
            "新手期": 0,
            "總力戰": 3,
            "大決戰": 3,
            "演習考試": 4,
            "戰術對抗": 0,
            "高難活動": 4,
            "泛用評級": 66,
            "IMG_URL": "https://i.imgur.com/l73PHbg.png"
        },
        "白石 詠葉(ウタハ/Utaha)": {
            "屬性": "貫通",
            "裝甲": "重裝",
            "武器": "SMG衝鋒槍",
            "定位": "後衛(召喚)",
            "新手期": 0,
            "總力戰": 4,
            "大決戰": 4,
            "演習考試": 3,
            "戰術對抗": 4,
            "高難活動": 2,
            "泛用評級": 70,
            "IMG_URL": "https://i.imgur.com/vMzqNVi.png"
        },
        "鰐渕 亞伽裡(アカリ/Akari)": {
            "屬性": "爆發",
            "裝甲": "重裝",
            "武器": "AR突擊槍",
            "定位": "前衛(輸出AOE)",
            "新手期": 3,
            "總力戰": 3,
            "大決戰": 3,
            "演習考試": 3,
            "戰術對抗": 0,
            "高難活動": 3,
            "泛用評級": 60,
            "IMG_URL": "https://i.imgur.com/9XFecBF.png"
        },
        "尾刃 環奈(Kanna/カンナ)": {
            "屬性": "貫通",
            "裝甲": "重裝",
            "武器": "HG手槍",
            "定位": "後衛(輔輸出)",
            "新手期": 0,
            "總力戰": 4,
            "大決戰": 4,
            "演習考試": 3,
            "戰術對抗": 0,
            "高難活動": 3,
            "泛用評級": 70,
            "IMG_URL": "https://i.imgur.com/rwIr16h.png"
        },
        "錠前 沙織(サオリ/Saori)": {
            "屬性": "爆發",
            "裝甲": "特殊",
            "武器": "AR突擊槍",
            "定位": "前衛(輸出)",
            "新手期": 3,
            "總力戰": 3,
            "大決戰": 4,
            "演習考試": 3,
            "戰術對抗": 4,
            "高難活動": 3,
            "泛用評級": 66,
            "IMG_URL": "https://i.imgur.com/n5nyoKB.png"
        },
        "秤 敦子(アツコ/Atsuko)": {
            "屬性": "爆發",
            "裝甲": "特殊",
            "武器": "SMG衝鋒槍",
            "定位": "前衛(補師坦)",
            "新手期": 4,
            "總力戰": 4,
            "大決戰": 4,
            "演習考試": 4,
            "戰術對抗": 5,
            "高難活動": 3,
            "泛用評級": 83,
            "IMG_URL": "https://i.imgur.com/hSiLX7X.png"
        },
        "戒野 美咲(ミサキ/Misaki)": {
            "屬性": "爆發",
            "裝甲": "特殊",
            "武器": "RL火箭發射器",
            "定位": "前衛(輸出)",
            "新手期": 2,
            "總力戰": 3,
            "大決戰": 3,
            "演習考試": 0,
            "戰術對抗": 0,
            "高難活動": 2,
            "泛用評級": 56,
            "IMG_URL": "https://i.imgur.com/BGvdzqJ.png"
        },
        "槌永 日和(ヒヨリ/Hiyori)": {
            "屬性": "爆發",
            "裝甲": "輕裝",
            "武器": "SR狙擊槍",
            "定位": "後衛(破防)",
            "新手期": 0,
            "總力戰": 3,
            "大決戰": 3,
            "演習考試": 0,
            "戰術對抗": 0,
            "高難活動": 0,
            "泛用評級": 60,
            "IMG_URL": "https://i.imgur.com/OTAom3G.png"
        },
        "黑崎 小雪(コユキ/Koyuki)": {
            "屬性": "神秘",
            "裝甲": "重裝",
            "武器": "MG機槍",
            "定位": "前衛(輸出AOE)",
            "新手期": 3,
            "總力戰": 3,
            "大決戰": 4,
            "演習考試": 3,
            "戰術對抗": 3,
            "高難活動": 2,
            "泛用評級": 60,
            "IMG_URL": "https://i.imgur.com/TutEJ83.png"
        },
        "明星 陽葵(ヒマリ/Himari)": {
            "屬性": "貫通",
            "裝甲": "輕裝",
            "武器": "HG手槍",
            "定位": "後衛(輔助)",
            "新手期": 0,
            "總力戰": 6,
            "大決戰": 5,
            "演習考試": 6,
            "戰術對抗": 6,
            "高難活動": 6,
            "泛用評級": 101,
            "IMG_URL": "https://i.imgur.com/Zu4ooJ2.png"
        },
        "生塩 乃愛(ノア/Noa)": "https://i.imgur.com/Y3eUOMO.png",
        "各務 千尋(チヒロ/Chihiro)": "https://i.imgur.com/RGQaGtW.png",
        "貓塚 響(ヒビキ/Hibiki)": "https://i.imgur.com/xdgOn2v.png",
        "才羽 綠(ミドリ/Midori)": "https://i.imgur.com/fZBpdPb.png",
        "花岡 柚子(ユズ/Yuzu)": "https://i.imgur.com/AbjJtaA.png",
        "角楯 花凜(カリン/Karin)": "https://i.imgur.com/M5406Yp.png",
        "小塗 真紀(マキ/Maki)": "https://i.imgur.com/p29odCU.png",
        "乙花 堇(スミレ/Sumire)": "https://i.imgur.com/3zQMMHM.png",
        "美甘 寧瑠(ネル/Neru)": "https://i.imgur.com/tzlYA0F.png",
        "鬼怒川 佳澄(カスミ/Kasumi)": "https://i.imgur.com/vD8Xtcg.png",
        "下倉 惠(メグ/Megu)": "https://i.imgur.com/xBUpHcR.png",
        "棗 伊呂波(イロハ/Iroha)": "https://i.imgur.com/oCmhVOR.png",
        "冰室 瀨奈(セナ/Sena)": "https://i.imgur.com/tRUFmb0.png",
        "銀鏡 伊織(イオリ/Iori)": "https://i.imgur.com/f8aXHIg.png",
        "黒舘 羽留奈(ハルナ/Haruna)": "https://i.imgur.com/JiB6dGh.png",
        "天雨 亞子(アコ/Ako)": "https://i.imgur.com/EWmfeBS.png",
        "陸八魔 亞瑠(アル/Aru)": "https://i.imgur.com/OWJOe52.png",
        "空崎 陽奈(ヒナ/Hina)": "https://i.imgur.com/oNgGPZY.png",
        "獅子堂 泉(イズミ/Izumi)": "https://i.imgur.com/UTtYLPb.png",
        "仲正 一花(イチカ/Ichika)": "https://i.imgur.com/FaNlpHU.png",
        "宇澤 澪紗(レイサ/Reisa)": "https://i.imgur.com/gvB7WXA.png",
        "歌住 櫻子 (サクラコ/Sakurako)": "https://i.imgur.com/H5w6K2v.png",
        "蒼森 美禰(ミネ/Mine)": "https://i.imgur.com/aBz00T4.png",
        "杏山 千紗(カズサ/Kazusa)": "https://i.imgur.com/BTI7Q1O.png",
        "古關 憂(ウイ/Ui)": "https://i.imgur.com/RXjZ7tP.png",
        "若葉 日向(ヒナタ/Hinata)": "https://i.imgur.com/ZholF0D.png",
        "白洲 梓(アズサ/Azusa)": "https://i.imgur.com/OfvQN6V.png",
        "下江 小春(コハル/Koharu)": "https://i.imgur.com/jEX02WF.png",
        "柚鳥 夏(ナツ/Natsu)": "https://i.imgur.com/Zks1Zp5.png",
        "阿慈谷 日步美(ヒフミ/Hifumi)": "https://i.imgur.com/AKRPN1y.png",
        "靜山 麻白(マシロ/Mashiro)": "https://i.imgur.com/oiW8TpW.png",
        "劍先 弦生(ツルギ/Tsurugi)": "https://i.imgur.com/EOzj700.png",
        "砂狼 白子(シロコ/Shiroko)": "https://i.imgur.com/KpAbIA2.png",
        "小鳥遊 星野(ホシノ/Hoshino)": "https://i.imgur.com/65X79FV.png",
        "姫木 愛瑠(メル/Meru)": "https://i.imgur.com/YWd9Aiv.png",
        "安守 實裡(ミノリ/Minori)": "https://i.imgur.com/mXwFLqw.png",
        "間宵 時雨(シグレ/Shigure)": "https://i.imgur.com/PWZRxc5.png",
        "池倉 瑪麗娜(マリナ/Marina)": "https://i.imgur.com/IAAuJdO.png",
        "連河 潔莉諾(チェリノ/Cherino)": "https://i.imgur.com/IeS92Y2.png",
        "裡浜 海花(ウミカ/Umika)": "https://i.imgur.com/qa6p7gO.png",
        "不破 蓮華(レンゲ/Renge)": "https://i.imgur.com/j0LoqVa.png",
        "桐生 桔梗(キキョウ/Kikyo)": "https://i.imgur.com/5fhGt4S.png",
        "勘解由小路 紫(ユカリ/Yukari)": "https://i.imgur.com/xXFk05p.png",
        "桑上 佳穗(カホ/Kaho)": "https://i.imgur.com/P7OMzjB.png",
        "大野 月夜(ツクヨ/Tsukuyo)": "https://i.imgur.com/dzVp2lB.png",
        "勇美 楓(カエデ/Kaede)": "https://i.imgur.com/1FVtGLh.png",
        "水羽 三森(ミモリ/Mimori)": "https://i.imgur.com/32eO4zF.png",
        "久田 伊樹菜(イズナ/Izuna)": "https://i.imgur.com/taOzmJr.png",
        "近衛 美奈(ミナ/Mina)": "https://i.imgur.com/NZnVRIP.png",
        "朱城 瑠美(ルミ/Rumi)": "https://i.imgur.com/etaJZCM.png",
        "春原 心菜 (ココナ/Kokona)": "https://i.imgur.com/NR3z4Xh.png",
        "春原 旬(シュン/Shun)": "https://i.imgur.com/F9NRIDQ.png",
        "藥子 沙耶(サヤ/Saya)": "https://i.imgur.com/V0blfQW.png",
        "才羽 桃井(モモイ/Momoi)": "https://i.imgur.com/7lp7kto.png",
        "早瀨 優香(ユウカ/Yuka)": "https://i.imgur.com/NZt787J.png",
        "一之瀨 明日奈(アスナ/Asuna)": "https://i.imgur.com/Iz99NkE.png",
        "淺黃 無月(ムツキ/Mutsuki)": "https://i.imgur.com/QwLppBF.png",
        "赤司 淳子(ジュンコ/Junko)": "https://i.imgur.com/ITui0ot.png",
        "火宮 千夏(チナツ/Chinatsu)": "https://i.imgur.com/sCJmlg4.png",
        "伊草 遙香(ハルカ/Haruka)": "https://i.imgur.com/D2jhZYo.png",
        "鬼方 佳世子(カヨコ/Kayoko)": "https://i.imgur.com/ukZnXAt.png",
        "牛牧 茱莉(ジュリ/Juri)": "https://i.imgur.com/ZBS15oT.png",
        "愛清 風華(フウカ/Fuuka)": "https://i.imgur.com/AI3a1LM.png",
        "守月 鈴美(スズミ/Suzumi)": "https://i.imgur.com/vgrnply.png",
        "羽川 蓮實(ハスミ/Hasumi)": "https://i.imgur.com/rEZBLoB.png",
        "鷲見 芹奈(セリナ/Serina)": "https://i.imgur.com/iHpd91O.png",
        "朝顏 花繪(ハナエ/Hanae)": "https://i.imgur.com/IkVevj7.png",
        "伊落 瑪麗(マリー/Mari)": "https://i.imgur.com/ZDjKX2M.png",
        "浦和 花子(ハナコ/Hanako)": "https://i.imgur.com/zO1nw3v.png",
        "伊原木 喜美(ヨシミ/Yoshimi)": "https://i.imgur.com/Z7qbaXK.png",
        "栗村 愛莉(アイリ/Airi)": "https://i.imgur.com/3jQqz9e.png",
        "円堂 志美子(シミコ/Shimiko)": "https://i.imgur.com/tJvFf3c.png",
        "黑見 茜香(セリカ/Serika)": "https://i.imgur.com/UyhJZGG.png",
        "十六夜 野乃美(ノノミ/nonomi)": "https://i.imgur.com/oBBjRFw.png",
        "奧空 綾音(アヤネ/Ayane)": "https://i.imgur.com/bAmdr4F.png",
        "春日 椿(ツバキ/Tsubaki)": "https://i.imgur.com/ubzsjmJ.png",
        "和樂 知世(チセ/Chise)": "https://i.imgur.com/58ibUAU.png",
        "朝比奈 菲娜(フィーナ/Pina)": "https://i.imgur.com/qcm6Zr8.png",
        "河和 靜子(シズコ/Shizuko)": "https://i.imgur.com/gQJglcS.png",
        "中務 桐乃(キリノ/Kirino)": "https://i.imgur.com/TLONZkL.png",
        "秋泉 紅葉(モミジ/Momiji)": "https://i.imgur.com/HiVkevf.png",
        "千鳥 三千留(ミチル/Michiru)": "https://i.imgur.com/I0ySkvc.png",
        "狐坂 若藻(ワカモ/Wakamo)": "https://i.imgur.com/8yrLgYE.png",
        "合歓垣 吹雪(フブキ/Fubuki)": "https://i.imgur.com/0n7rTeP.png",
        "羽沼 真琴(マコト/Makoto)": "https://i.imgur.com/LyOQVcI.png",
        "丹花 伊吹(イブキ/Ibuki)": "https://i.imgur.com/J9xMoa1.png",
        "桐藤 渚(ナギサ/Nagisa)": "https://i.imgur.com/ooXYg0A.png",
        "聖園 彌香(ミカ/Mika)": "https://i.imgur.com/IwNs0JU.png",
        "佐藤 智惠(トモエ/Tomoe)": "https://i.imgur.com/0QvYtWJ.png",
        "天見 和香(ノドカ/Nodoka)": "https://i.imgur.com/sKziEiQ.png",
        "禦坂 美琴(みこと/Mikoto)": "https://i.imgur.com/T0hA1uP.png",
        "食蜂 操祈(みさき/Misaki)": "https://i.imgur.com/1X72yac.png",
        "佐天 涙子(るいこ/Ruiko)": "https://i.imgur.com/haNeFUo.png",
        "初音 未來(ミク/Miku)": "https://i.imgur.com/ZdUS9h6.png",
        "空井 咲希(サキ/Saki).泳裝": "https://i.imgur.com/NkYbvnG.png",
        "和泉元 英美.泳裝(エイミ/Eimi)": "https://i.imgur.com/X09dkXA.png",
        "月雪 都子(ミヤコ/Miyako).泳裝": "https://i.imgur.com/scVbltH.png",
        "阿慈谷 日步美(ヒフミ/Hifumi).泳裝": "https://i.imgur.com/czMK28A.png",
        "砂狼 白子(シロコ/Shiroko).泳裝": "https://i.imgur.com/6xGEtpu.png",
        "十六夜 野乃美(ノノミ/Nonomi).泳裝": "https://i.imgur.com/wRuXFoz.png",
        "狐坂 若藻(ワカモ/Wakamo).泳裝": "https://i.imgur.com/JKT5Vyx.png",
        "水羽 三森(ミモリ/Mimori).泳裝": "https://i.imgur.com/u7VdrgN.png",
        "霞沢 美優(ミユ/Miyu).泳裝": "https://i.imgur.com/9Lwy9Hz.png",
        "小鳥遊 星野(ホシノ/Hoshino).泳裝": "https://i.imgur.com/3f0Xueu.png",
        "奧空 綾音(アヤネ/Ayane).泳裝": "https://i.imgur.com/rqLx3Ij.png",
        "久田 伊樹菜(イズナ/Izuna).泳裝": "https://i.imgur.com/QOZ9tmT.png",
        "和樂 知世(チセ/Chise).泳裝": "https://i.imgur.com/l7Jp8m9.png",
        "河和 靜子(シズコ/Shizuko).泳裝": "https://i.imgur.com/J5t4zh9.png",
        "空崎 陽奈(ヒナ/Hina).泳裝": "https://i.imgur.com/P1HOj0A.png",
        "銀鏡 伊織(イオリ/Iori).泳裝": "https://i.imgur.com/9S35Y4Z.png",
        "獅子堂 泉(イズミ/Izumi).泳裝": "https://i.imgur.com/NGRza6N.png",
        "浦和 花子(ハナコ/Hanako).泳裝": "https://i.imgur.com/N2M9CCg.png",
        "古關 憂(ウイ/Ui).泳裝": "https://i.imgur.com/sjlDmgA.png",
        "若葉 日向(ヒナタ/Hinata).泳裝": "https://i.imgur.com/Lc05at0.png",
        "下江 小春(コハル/Koharu).泳裝": "https://i.imgur.com/M8JWKHE.png",
        "白洲 梓(アズサ/Azusa).泳裝": "https://i.imgur.com/6539qnA.png",
        "靜山 麻白(マシロ/Mashiro).泳裝": "https://i.imgur.com/aUtilY7.png",
        "劍先 弦生(ツルギ/Tsurugi).泳裝": "https://i.imgur.com/lsWy1Am.png",
        "鰐渕 亞伽裡.正月(アカリ/Akari)": "https://i.imgur.com/92SRzky.png",
        "伊草 遙香(ハルカ/Haruka).正月": "https://i.imgur.com/UHn2wZK.png",
        "鬼方 佳世子(カヨコ/Kayoko).正月": "https://i.imgur.com/zI5hKVU.png",
        "黑見 茜香(セリカ/Serika).正月": "https://i.imgur.com/7lWhybk.png",
        "黒舘 羽留奈.正月(ハルナ/Haruna)": "https://i.imgur.com/rFygxpr.png",
        "愛清 風華.正月(フウカ/Fuuka)": "https://i.imgur.com/vjxAAT3.png",
        "赤司 淳子.正月(ジュンコ/Junko)": "https://i.imgur.com/s2XAVBg.png",
        "陸八魔 亞瑠(アル/Aru).正月": "https://i.imgur.com/wquqBrJ.png",
        "淺黃 無月(ムツキ/Mutsuki).正月": "https://i.imgur.com/TZO4rar.png",
        "飛鳥馬 季.兔女郎(トキ/Toki)": "https://i.imgur.com/tOWAhmQ.png",
        "室笠 朱音.兔女郎(アカネ/Akane)": "https://i.imgur.com/CYoQZ3L.png",
        "一之瀬 明日奈.兔女郎(アスナ/Asuna)": "https://i.imgur.com/ha3UVms.png",
        "美甘 寧瑠(ネル/Neru).兔女郎": "https://i.imgur.com/sS0o2fk.png",
        "角楯 花凜(カリン/Karin).兔女郎": "https://i.imgur.com/IseE3OQ.png",
        "陸八魔 亞瑠(アル/Aru).禮服": "https://i.imgur.com/jVbtRJv.png",
        "鬼方 佳世子(カヨコ/Kayoko).禮服": "https://i.imgur.com/blFlHHt.png",
        "空崎 陽奈(ヒナ/Hina).禮服": "https://i.imgur.com/luFU27B.png",
        "天雨 亞子(アコ/Ako).禮服": "https://i.imgur.com/kS027LB.png",
        "黒舘 羽留奈.運動服(ハルナ/Haruna)": "https://i.imgur.com/08ms9hv.png",
        "早瀨 優香.運動服(ユウカ/Yuka)": "https://i.imgur.com/Y6RFjcP.png",
        "伊落 瑪麗.運動服(マリー/Mari)": "https://i.imgur.com/iA4sGYV.png",
        "羽川 蓮實.運動服(ハスミ/Hasumi)": "https://i.imgur.com/4C4ZWDu.png",
        "火宮 千夏 (チナツ/Chinatsu).溫泉": "https://i.imgur.com/txgu1xc.png",
        "間宵 時雨(シグレ/Shigure).溫泉": "https://i.imgur.com/lfLP2cS.png",
        "連河 潔莉諾(チェリノ/Cherino).溫泉": "https://i.imgur.com/xAX5Tww.png",
        "天見 和香(ノドカ/Nodoka).溫泉": "https://i.imgur.com/HUMZmbP.png",
        "豊見 亞都梨.應援團(コトリ/Kotori)": "https://i.imgur.com/SmglmHE.png",
        "白石 詠葉.應援團(ウタハ/Utaha)": "https://i.imgur.com/uVSYS0x.png",
        "貓塚 響.應援團(ヒビキ/Hibiki)": "https://i.imgur.com/RicFEGk.png",
        "杏山 千紗(カズサ/Kazusa).樂隊": "https://i.imgur.com/qocblfN.png",
        "伊原木 喜美(ヨシミ/Yoshimi).樂隊": "https://i.imgur.com/xkaMImI.png",
        "栗村 愛莉(アイリ/Airi).樂隊": "https://i.imgur.com/pqZ8W4q.png",
        "音瀨 小玉(コタマ/Kotama).露營": "https://i.imgur.com/40gKgzX.png",
        "小鉤 晴(ハレ/Hare）.露營": "https://i.imgur.com/wDoZxzI.png",
        "天童 愛麗絲.女僕(アリス/Arisu)": "https://i.imgur.com/pUoTmJb.png",
        "花岡 柚子.女僕(ユズ/Yuzu)": "https://i.imgur.com/4SnKGIM.png",
        "鷲見 芹奈(セリナ/Serina).聖誕節": "https://i.imgur.com/f1WNks5.png",
        "朝顏 花繪(ハナエ/Hanae).聖誕節": "https://i.imgur.com/3qHZREX.png",
        "砂狼 白子(シロコ/Shiroko).自行車裝": "https://i.imgur.com/kwgpaHL.png",
        "春日 椿(ツバキ/Tsubaki).導遊": "https://i.imgur.com/Q4aLYsm.png",
        "春原 旬(シュン/Shun).幼女": "https://i.imgur.com/KxqiWF6.png",
        "藥子 沙耶(サヤ/Saya).私服": "https://i.imgur.com/wtm4tO4.png"
    }
}